banner_kimwonjoon/__init__.py
banner_kimwonjoon/banner.py
banner_kimwonjoon-0.5.1.dist-info/METADATA
banner_kimwonjoon-0.5.1.dist-info/WHEEL
banner_kimwonjoon-0.5.1.dist-info/entry_points.txt
banner_kimwonjoon-0.5.1.dist-info/top_level.txt
banner_kimwonjoon-0.5.1.dist-info/RECORD
