Metadata-Version: 2.1
Name: banner_kimwonjoon
Version: 0.5.1
Summary: Default template for PDM package
Author-email: Kimwonjoon <kimpass189@gmail.com>
License: MIT
Project-URL: Homepage, https://github.com/Kimwonjoon/banner_kimwonjoon
Project-URL: Issues, https://github.com/Kimwonjoon/banner_kimwonjoon/issues
Requires-Python: >=3.9
Requires-Dist: pyfiglet >=1.0.2
